hcli_core/__init__.py
hcli_core/__main__.py
hcli_core/config.py
hcli_core/handler.py
hcli_core/hcliserver.py
hcli_core/hutils.py
hcli_core/logger.py
hcli_core/package.py
hcli_core/template.py
hcli_core/auth/__init__.py
hcli_core/auth/cli/__init__.py
hcli_core/auth/cli/authenticator.py
hcli_core/auth/cli/cli.py
hcli_core/auth/cli/credential.py
hcli_core/auth/cli/credentials
hcli_core/auth/cli/credentials.lock
hcli_core/auth/cli/service.py
hcli_core/auth/cli/template.json
hcli_core/cli/__init__.py
hcli_core/cli/cli.py
hcli_core/cli/template.json
hcli_core/data/hcli_core.1
hcli_core/haliot/__init__.py
hcli_core/haliot/hal.py
hcli_core/hcli/__init__.py
hcli_core/hcli/api.py
hcli_core/hcli/command.py
hcli_core/hcli/document.py
hcli_core/hcli/execution.py
hcli_core/hcli/finalexecution.py
hcli_core/hcli/option.py
hcli_core/hcli/parameter.py
hcli_core/hcli/profile.py
hcli_core/hcli/root.py
hcli_core/hcli/secondaryhome.py
hcli_core/hcli/semantic.py
hcli_core/sample/hfm/cli/__init__.py
hcli_core/sample/hfm/cli/chroot.py
hcli_core/sample/hfm/cli/cli.py
hcli_core/sample/hfm/cli/template.json
hcli_core/sample/hfm/cli/chroot/hello.json
hcli_core/sample/hptt/cli/__init__.py
hcli_core/sample/hptt/cli/channel.py
hcli_core/sample/hptt/cli/channels.json
hcli_core/sample/hptt/cli/channels.py
hcli_core/sample/hptt/cli/chroot.py
hcli_core/sample/hptt/cli/cli.py
hcli_core/sample/hptt/cli/data.py
hcli_core/sample/hptt/cli/template.json
hcli_core/sample/hptt/cli/scripts/listen.sh
hcli_core/sample/hptt/cli/scripts/watch.sh
hcli_core/sample/hub/cli/__init__.py
hcli_core/sample/hub/cli/cli.py
hcli_core/sample/hub/cli/data.py
hcli_core/sample/hub/cli/hub.json
hcli_core/sample/hub/cli/hub.py
hcli_core/sample/hub/cli/namespace.py
hcli_core/sample/hub/cli/template.json
hcli_core/sample/nw/cli/__init__.py
hcli_core/sample/nw/cli/cli.py
hcli_core/sample/nw/cli/data.py
hcli_core/sample/nw/cli/networks.py
hcli_core/sample/nw/cli/pool.py
hcli_core/sample/nw/cli/template.json
hcli_core-3.7.3.dist-info/LICENSE.txt
hcli_core-3.7.3.dist-info/METADATA
hcli_core-3.7.3.dist-info/WHEEL
hcli_core-3.7.3.dist-info/entry_points.txt
hcli_core-3.7.3.dist-info/top_level.txt
hcli_core-3.7.3.dist-info/RECORD
