Metadata-Version: 2.1
Name: hcli_core
Version: 3.7.3
Summary: An HCLI Connector that can be used to expose a REST API that behaves as a CLI, via hypertext command line interface (HCLI) semantics.
Author-email: Jeff Michaud <cometaj2@proton.me>
License: Copyright (c) 2017 Jeff Michaud
Project-URL: Homepage, https://github.com/cometaj2/hcli_core
Keywords: cli,client,server,connector,hypermedia,rest,generic,development
Classifier: Development Status :: 4 - Beta
Classifier: Intended Audience :: Developers
Classifier: Topic :: Software Development
Classifier: Programming Language :: Python :: 3.8
Classifier: Programming Language :: Python :: 3.9
Classifier: Programming Language :: Python :: 3.10
Classifier: Programming Language :: Python :: 3.11
Classifier: Programming Language :: Python :: 3.12
License-File: LICENSE.txt
Requires-Dist: falcon==4.0.2
Requires-Dist: portalocker==2.10.1
Requires-Dist: huckle<6.0.0,>=5.5.6
Requires-Dist: hcli-problem-details<1.0.0,>=0.2.0
